setup.py
pyds/__init__.py
pyds/sequences/__init__.py
pyds/sequences/stack.py
pyds/sequences/test_stack.py
ukonline.pyds.egg-info/PKG-INFO
ukonline.pyds.egg-info/SOURCES.txt
ukonline.pyds.egg-info/dependency_links.txt
ukonline.pyds.egg-info/top_level.txt