Metadata-Version: 1.1
Name: ukonline.pyds
Version: 0.0.1a2
Summary: Data structures implementations in Python for pedagogical purpose.
Home-page: https://github.com/ukonline/pyds
Author: UKOnline
Author-email: info@ukonline.be
License: GPLv3
Keywords: data-structures
Platform: UNKNOWN
Classifier: Development Status :: 3 - Alpha
Classifier: Environment :: Console
Classifier: Intended Audience :: Developers
Classifier: Intended Audience :: Education
Classifier: License :: OSI Approved :: GNU General Public License v3 (GPLv3)
Classifier: Programming Language :: Python :: 3.5
Classifier: Topic :: Software Development :: Libraries
